{"numTabs":36,"items":[{"verified":false,"w":2,"h":1,"icon":"https://webtw.poecdn.com/gen/image/WzI1LDE0LHsiZiI6IjJESXRlbXMvQmVsdHMvQ3J5c3RhbEJlbHQiLCJ3IjoyLCJoIjoxLCJzY2FsZSI6MX1d/1e9174ec8f/CrystalBelt.png","league":"標準模式","id":"f5e0fb3b9c586e2fe2ebf13e20ccf9e480f7ac588673ac5ddacd3292f7760789","name":"漩渦 縛帶","typeLine":"水晶腰帶","baseType":"水晶腰帶","rarity":"Rare","ilvl":79,"identified":true,"requirements":[{"name":"等級","values":[["79",0]],"displayMode":0,"type":62}],"implicitMods":["+61 最大能量護盾"],"explicitMods":["+32 最大能量護盾","+32% 冰冷抗性","+17% 閃電抗性","+29% 混沌抗性"],"frameType":2,"frameTypeId":"Rare","x":4,"y":10,"inventoryId":"Stash13"},{"verified":false,"w":2,"h":3,"icon":"https://webtw.poecdn.com/gen/image/WzI1LDE0LHsiZiI6IjJESXRlbXMvV2VhcG9ucy9PbmVIYW5kV2VhcG9ucy9TY2VwdGVycy9zY2VwdGVyNCIsInciOjIsImgiOjMsInNjYWxlIjoxfV0/c986bafb78/scepter4.png","league":"標準模式","id":"54f9663bcf5656f9f32c24daf8b5ccc204a65b10a0fa19767df62605029f0475","sockets":[{"group":0,"attr":"I","sColour":"B"},{"group":1,"attr":"D","sColour":"G"},{"group":2,"attr":"I","sColour":"B"}],"name":"蒼空 織術者","typeLine":"水晶權杖","baseType":"水晶權杖","rarity":"Rare","ilvl":81,"identified":true,"properties":[{"name":"權杖","values":[],"displayMode":0},{"name":"物理傷害","values":[["54-90",1]],"displayMode":0,"type":9},{"name":"暴擊率","values":[["8.00%",0]],"displayMode":0,"type":12},{"name":"每秒攻擊次數","values":[["1.25",0]],"displayMode":0,"type":13},{"name":"武器距離: {0} 米","values":[["1.1",0]],"displayMode":3,"type":14}],"requirements":[{"name":"等級","values":[["60",0]],"displayMode":0,"type":62},{"name":"力量","values":[["59",0]],"displayMode":1,"type":63},{"name":"智慧","values":[["85",0]],"displayMode":1,"type":65}],"implicitMods":["增加 30% 元素傷害"],"explicitMods":["+25 智慧","附加 19 至 38 物理傷害","法術附加 10 至 132 閃電傷害","增加 109% 法術暴擊率","全部閃電法術技能寶石等級 +1"],"craftedMods":["使用技能時觸發插槽中的 1 個法術，有 8 秒冷卻時間\n以此方式觸發的法術有 150% 更多消耗"],"frameType":2,"frameTypeId":"Rare","x":6,"y":0,"inventoryId":"Stash13","socketedItems":[]},{"verified":false,"w":2,"h":2,"icon":"https://webtw.poecdn.com/gen/image/WzI1LDE0LHsiZiI6IjJESXRlbXMvQXJtb3Vycy9HbG92ZXMvR2xvdmVzU3RyRGV4MiIsInciOjIsImgiOjIsInNjYWxlIjoxfV0/0bb5dd1e50/GlovesStrDex2.png","league":"標準模式","id":"1dbb68195846802db83ad746908f36b8627a4ca66516c734fda2f21cfda34fbf","sockets":[{"group":0,"attr":"I","sColour":"B"},{"group":0,"attr":"S","sColour":"R"},{"group":0,"attr":"S","sColour":"R"},{"group":0,"attr":"S","sColour":"R"}],"name":"刺荊 掌爪","typeLine":"火蝮鱗手套","baseType":"火蝮鱗手套","rarity":"Rare","ilvl":72,"identified":true,"properties":[{"name":"護甲","values":[["131",1]],"displayMode":0,"type":16},{"name":"閃避值","values":[["133",1]],"displayMode":0,"type":17}],"requirements":[{"name":"等級","values":[["59",0]],"displayMode":0,"type":62},{"name":"力量","values":[["45",0]],"displayMode":1,"type":63},{"name":"敏捷","values":[["45",0]],"displayMode":1,"type":64}],"explicitMods":["+21 點護甲","+23 點閃避值","+29% 火焰抗性","+33% 冰冷抗性","+39% 閃電抗性","0.2% 物理攻擊傷害偷取魔力"],"craftedMods":["+54 最大生命"],"frameType":2,"frameTypeId":"Rare","x":8,"y":3,"inventoryId":"Stash13","socketedItems":[]},{"verified":false,"w":1,"h":1,"icon":"https://webtw.poecdn.com/gen/image/WzI1LDE0LHsiZiI6IjJESXRlbXMvSmV3ZWxzL2Jhc2ljZGV4IiwidyI6MSwiaCI6MSwic2NhbGUiOjF9XQ/9ed22a2b94/basicdex.png","league":"標準模式","id":"6fd8222a8efdaad8d5cb5c2ad6e11773c16fff3c9b519bfd1808df49b2aea0d1","name":"耀眼繁花","typeLine":"翠綠珠寶","baseType":"翠綠珠寶","rarity":"Rare","ilvl":84,"identified":true,"corrupted":true,"implicitMods":["增加 2% 技能的保留效用","傷害穿透 1% 元素抗性"],"explicitMods":["+14 敏捷","增加 6% 藥劑效果持續時間","增加 2% 技能的魔力保留效用"],"descrText":"放置到一個天賦樹的珠寶插槽中以產生效果。右鍵點擊以移出插槽。","frameType":2,"frameTypeId":"Rare","x":9,"y":8,"inventoryId":"Stash13"},{"verified":false,"w":2,"h":1,"icon":"https://webtw.poecdn.com/gen/image/WzI1LDE0LHsiZiI6IjJESXRlbXMvQmVsdHMvQWJ5c3NCZWx0IiwidyI6MiwiaCI6MSwic2NhbGUiOjF9XQ/973fb5fe7a/AbyssBelt.png","league":"標準模式","id":"7c05ad8243500c09fdbcf79edcf2fa8b3febb9026512ee8c3752de585912610f","sockets":[{"group":0,"attr":"A","sColour":"A"}],"name":"猛攻 腹套","typeLine":"冥河腰帶","baseType":"冥河腰帶","rarity":"Rare","ilvl":72,"identified":true,"requirements":[{"name":"等級","values":[["52",0]],"displayMode":0,"type":62}],"implicitMods":["有 1 個深淵插槽"],"explicitMods":["+42 力量","+99 最大生命","+33% 閃電抗性","+13% 混沌抗性","反射 2 物理傷害給近戰攻擊者"],"craftedMods":["+45 最大魔力"],"frameType":2,"frameTypeId":"Rare","x":10,"y":2,"inventoryId":"Stash13","socketedItems":[]},{"verified":false,"w":2,"h":2,"icon":"https://webtw.poecdn.com/gen/image/WzI1LDE0LHsiZiI6IjJESXRlbXMvQXJtb3Vycy9Cb290cy9Cb290c1N0ckRleDIiLCJ3IjoyLCJoIjoyLCJzY2FsZSI6MX1d/d5b5430d4c/BootsStrDex2.png","league":"標準模式","id":"dc21d68693e85cd179a17342cfd0f6970efc3929e015c1b69bcc8171248197ab","sockets":[{"group":0,"attr":"S","sColour":"R"},{"group":1,"attr":"S","sColour":"R"},{"group":1,"attr":"S","sColour":"R"},{"group":1,"attr":"I","sColour":"B"}],"name":"鷹翼 之足","typeLine":"火蝮鱗長靴","baseType":"火蝮鱗長靴","rarity":"Rare","ilvl":82,"identified":true,"properties":[{"name":"護甲","values":[["136",1]],"displayMode":0,"type":16},{"name":"閃避值","values":[["136",1]],"displayMode":0,"type":17}],"requirements":[{"name":"等級","values":[["59",0]],"displayMode":0,"type":62},{"name":"力量","values":[["56",0]],"displayMode":1,"type":63},{"name":"敏捷","values":[["56",0]],"displayMode":1,"type":64}],"explicitMods":["增加 28% 護甲與閃避","+70 最大生命","+43% 火焰抗性","+38% 冰冷抗性","增加 30% 移動速度","增加 25% 暈眩恢復和格擋恢復"],"frameType":2,"frameTypeId":"Rare","x":6,"y":8,"inventoryId":"Stash13","socketedItems":[]},{"verified":false,"w":1,"h":1,"icon":"https://webtw.poecdn.com/gen/image/WzI1LDE0LHsiZiI6IjJESXRlbXMvUmluZ3MvQW1ldGh5c3RSaW5nIiwidyI6MSwiaCI6MSwic2NhbGUiOjF9XQ/804d781735/AmethystRing.png","league":"標準模式","id":"f372d4138c2ae9708a4ba024f120f3e08817adf81e52fb643fcbe07b9f74b164","name":"暴風 閃耀之指","typeLine":"紫晶戒指","baseType":"紫晶戒指","rarity":"Rare","ilvl":73,"identified":true,"requirements":[{"name":"等級","values":[["35",0]],"displayMode":0,"type":62}],"implicitMods":["+13% 混沌抗性"],"explicitMods":["+28 力量","+75 最大生命","+9% 全部元素抗性","+12% 火焰抗性"],"frameType":2,"frameTypeId":"Rare","x":0,"y":3,"inventoryId":"Stash13"},{"verified":false,"w":1,"h":1,"icon":"https://webtw.poecdn.com/gen/image/WzI1LDE0LHsiZiI6IjJESXRlbXMvQW11bGV0cy9UYWxpc21hbkJsYWNrNSIsInciOjEsImgiOjEsInNjYWxlIjoxfV0/48fab16b73/TalismanBlack5.png","league":"標準模式","id":"bb1b082441752f39185960f83483411603d8b1bfb6ed9489f57228b1194cd578","name":"遺忘 安魂符","typeLine":"齒鯊魔符","baseType":"齒鯊魔符","rarity":"Rare","ilvl":72,"identified":true,"corrupted":true,"requirements":[{"name":"等級","values":[["54",0]],"displayMode":0,"type":62}],"talismanTier":2,"implicitMods":["增加 11% 最大生命"],"explicitMods":["增加 15% 最大能量護盾","+17% 火焰抗性","+24% 閃電抗性","+14% 混沌抗性"],"craftedMods":["+54 最大生命"],"flavourText":["初代是種永恆的存在\r","在他們的血液中沒有時間的流逝\r","在他們的臉龐上沒有焦慮的痕跡\r","若要飲下他們的血即是飲下時間\r","- 狼王"],"frameType":2,"frameTypeId":"Rare","x":11,"y":3,"inventoryId":"Stash13"},{"verified":false,"w":1,"h":1,"icon":"https://webtw.poecdn.com/gen/image/WzI1LDE0LHsiZiI6IjJESXRlbXMvUmluZ3MvRGlhbW9uZFJpbmciLCJ3IjoxLCJoIjoxLCJzY2FsZSI6MSwic3ludGhlc2lzZWQiOnRydWV9XQ/3a20b692fe/DiamondRing.png","league":"標準模式","id":"1e9f6304cff5e7855a79b5cda420869543e3e6e6feef9f5ce31e8e5a9e7eb295","synthesised":true,"name":"靈魂 之眼","typeLine":"追憶之 寶鑽戒指","baseType":"寶鑽戒指","rarity":"Rare","ilvl":82,"identified":true,"requirements":[{"name":"等級","values":[["64",0]],"displayMode":0,"type":62}],"implicitMods":["增加 8% 冰冷傷害"],"explicitMods":["+22 智慧","+66 點閃避值","+74 最大生命","+42% 火焰抗性","+26% 閃電抗性"],"craftedMods":["+39 最大魔力","6% 的承受傷害補償為魔力"],"frameType":2,"frameTypeId":"Rare","x":1,"y":3,"inventoryId":"Stash13"},{"verified":false,"w":2,"h":2,"icon":"https://webtw.poecdn.com/gen/image/WzI1LDE0LHsiZiI6IjJESXRlbXMvQXJtb3Vycy9Cb290cy9Cb290c1N0cjMiLCJ3IjoyLCJoIjoyLCJzY2FsZSI6MX1d/56efa25c50/BootsStr3.png","league":"標準模式","id":"0423927bfd324fdcbd530f041aed3e3e1f58922c831273cdb73323048eabec61","sockets":[{"group":0,"attr":"D","sColour":"G"},{"group":0,"attr":"S","sColour":"R"}],"name":"霸主 涼靴","typeLine":"遠古脛甲","baseType":"遠古脛甲","rarity":"Rare","ilvl":85,"identified":true,"properties":[{"name":"護甲","values":[["198",1]],"displayMode":0,"type":16}],"requirements":[{"name":"等級","values":[["48",0]],"displayMode":0,"type":62},{"name":"力量","values":[["82",0]],"displayMode":1,"type":63}],"explicitMods":["增加 31% 護甲","+57 最大生命","每秒 5.3 基本魔力回復","+38% 火焰抗性","+37% 冰冷抗性","增加 30% 移動速度","增加 12% 暈眩恢復和格擋恢復"],"frameType":2,"frameTypeId":"Rare","x":4,"y":8,"inventoryId":"Stash13","socketedItems":[]},{"verified":false,"w":2,"h":1,"icon":"https://webtw.poecdn.com/gen/image/WzI1LDE0LHsiZiI6IjJESXRlbXMvQmVsdHMvQmVsdDMiLCJ3IjoyLCJoIjoxLCJzY2FsZSI6MX1d/93af17affd/Belt3.png","league":"標準模式","id":"55b6c29819815b25290ffcdbc5acdd53a10dfe5bdde0008c238e33c7f7014625","name":"疫源 保護符","typeLine":"皮革腰帶","baseType":"皮革腰帶","rarity":"Rare","ilvl":69,"identified":true,"requirements":[{"name":"等級","values":[["54",0]],"displayMode":0,"type":62}],"implicitMods":["+35 最大生命"],"explicitMods":["+146 點護甲","+32% 火焰抗性","+38% 冰冷抗性","+35% 閃電抗性"],"craftedMods":["+45 最大生命"],"frameType":2,"frameTypeId":"Rare","x":2,"y":8,"inventoryId":"Stash13"},{"verified":false,"w":2,"h":2,"icon":"https://webtw.poecdn.com/gen/image/WzI1LDE0LHsiZiI6IjJESXRlbXMvQXJtb3Vycy9Cb290cy9Ud29Ub25lZEJvb3RzIiwidyI6MiwiaCI6Miwic2NhbGUiOjF9XQ/93a61b5672/TwoTonedBoots.png","league":"標準模式","id":"054e3f8f110a0c51394ec63078ce0a03744b9585c822b573eef2bfa63dc5f8e7","sockets":[{"group":0,"attr":"S","sColour":"R"},{"group":0,"attr":"D","sColour":"G"},{"group":0,"attr":"D","sColour":"G"},{"group":0,"attr":"S","sColour":"R"}],"name":"符紋 疾影","typeLine":"異色鞋","baseType":"異色鞋","rarity":"Rare","ilvl":70,"identified":true,"properties":[{"name":"閃避值","values":[["126",0]],"displayMode":0,"type":17},{"name":"能量護盾","values":[["26",0]],"displayMode":0,"type":18}],"requirements":[{"name":"等級","values":[["70",0]],"displayMode":0,"type":62},{"name":"敏捷","values":[["62",0]],"displayMode":1,"type":64},{"name":"智慧","values":[["62",0]],"displayMode":1,"type":65}],"implicitMods":["+12% 冰冷與閃電抗性"],"explicitMods":["+44 最大魔力","增加 11% 物品稀有度","+35% 火焰抗性","+39% 冰冷抗性","+35% 閃電抗性"],"craftedMods":["+66 最大生命"],"frameType":2,"frameTypeId":"Rare","x":10,"y":7,"inventoryId":"Stash13","socketedItems":[]},{"verified":false,"w":1,"h":1,"icon":"https://webtw.poecdn.com/gen/image/WzI1LDE0LHsiZiI6IjJESXRlbXMvUmluZ3MvQW1ldGh5c3RSaW5nIiwidyI6MSwiaCI6MSwic2NhbGUiOjF9XQ/804d781735/AmethystRing.png","league":"標準模式","id":"960e886596312511c383c1f5ce168760dedb463b87dbdfad1bd380fac52f9906","influences":{"shaper":true},"shaper":true,"name":"心靈 靈環","typeLine":"紫晶戒指","baseType":"紫晶戒指","rarity":"Rare","ilvl":85,"identified":true,"requirements":[{"name":"等級","values":[["54",0]],"displayMode":0,"type":62}],"implicitMods":["+9% 混沌抗性"],"explicitMods":["攻擊附加 1 至 2 物理傷害","攻擊附加 3 至 42 閃電傷害","+41% 火焰抗性","+25% 冰冷抗性","+8% 閃電抗性"],"craftedMods":["+41 最大生命"],"frameType":2,"frameTypeId":"Rare","x":11,"y":1,"inventoryId":"Stash13"},{"verified":false,"w":1,"h":1,"icon":"https://webtw.poecdn.com/gen/image/WzI1LDE0LHsiZiI6IjJESXRlbXMvSmV3ZWxzL2Jhc2ljaW50IiwidyI6MSwiaCI6MSwic2NhbGUiOjEsInN5bnRoZXNpc2VkIjp0cnVlfV0/870966c313/basicint.png","league":"標準模式","id":"d7a4727c745b48bcf4bdb021f0ccf0449e62d81e8219d8e2e6286174a928214e","synthesised":true,"name":"榮耀贈禮","typeLine":"追憶之 鈷藍珠寶","baseType":"鈷藍珠寶","rarity":"Rare","ilvl":83,"identified":true,"implicitMods":["增加 2% 混沌傷害","增加 4% 全域暴擊率"],"explicitMods":["增加 6% 最大生命","增加 3% 攻擊與施放速度","+10% 火焰與閃電抗性"],"descrText":"放置到一個天賦樹的珠寶插槽中以產生效果。右鍵點擊以移出插槽。","frameType":2,"frameTypeId":"Rare","x":10,"y":1,"inventoryId":"Stash13"},{"verified":false,"w":2,"h":2,"icon":"https://webtw.poecdn.com/gen/image/WzI1LDE0LHsiZiI6IjJESXRlbXMvQXJtb3Vycy9Cb290cy9Cb290c0RleDMiLCJ3IjoyLCJoIjoyLCJzY2FsZSI6MX1d/f2e9a30d4a/BootsDex3.png","league":"標準模式","id":"feb6fe77217bac6da535f4b4bcc3ca3dfed4474b7a8ecd9346e4e1ef4b00cbb7","sockets":[{"group":0,"attr":"D","sColour":"G"},{"group":0,"attr":"D","sColour":"G"},{"group":0,"attr":"S","sColour":"R"},{"group":0,"attr":"I","sColour":"B"}],"name":"宿敵 風喚","typeLine":"妖羽皮短靴","baseType":"妖羽皮短靴","rarity":"Rare","ilvl":86,"identified":true,"properties":[{"name":"閃避值","values":[["706",1]],"displayMode":0,"type":17}],"requirements":[{"name":"等級","values":[["78",0]],"displayMode":0,"type":62},{"name":"敏捷","values":[["153",0]],"displayMode":1,"type":64}],"explicitMods":["+14% 壓抑法術傷害率","+55 敏捷","增加 100% 閃避值","+127 最大生命","增加 30% 移動速度"],"craftedMods":["+33% 閃電抗性"],"frameType":2,"frameTypeId":"Rare","x":6,"y":10,"inventoryId":"Stash13","socketedItems":[]},{"verified":false,"w":2,"h":1,"icon":"https://webtw.poecdn.com/gen/image/WzI1LDE0LHsiZiI6IjJESXRlbXMvQmVsdHMvQmVsdDUiLCJ3IjoyLCJoIjoxLCJzY2FsZSI6MX1d/a513a7e6b4/Belt5.png","league":"標準模式","id":"e9c3a5094cc55a897e57296f4784d18b1613f898d0bb16f11935789a4ce6754e","name":"惡行 羈絆","typeLine":"重革腰帶","baseType":"重革腰帶","rarity":"Rare","ilvl":83,"identified":true,"corrupted":true,"requirements":[{"name":"等級","values":[["51",0]],"displayMode":0,"type":62}],"implicitMods":["增加 4% 力量","增加 6% 敏捷"],"explicitMods":["+12 力量","+141 最大生命","+16% 冰冷抗性","增加 14% 敵人暈眩時間"],"frameType":2,"frameTypeId":"Rare","x":10,"y":4,"inventoryId":"Stash13"},{"verified":false,"w":2,"h":2,"icon":"https://webtw.poecdn.com/gen/image/WzI1LDE0LHsiZiI6IjJESXRlbXMvQXJtb3Vycy9HbG92ZXMvR2xvdmVzRGV4SW50MyIsInciOjIsImgiOjIsInNjYWxlIjoxfV0/060b6ea395/GlovesDexInt3.png","league":"標準模式","id":"75372370144465a07fc8c2cdda64c9ed206dded1adf82909d685c19883727a7c","sockets":[{"group":0,"attr":"S","sColour":"R"},{"group":0,"attr":"S","sColour":"R"},{"group":0,"attr":"I","sColour":"B"},{"group":0,"attr":"D","sColour":"G"}],"name":"魔域 護指套","typeLine":"禁禮護手","baseType":"禁禮護手","rarity":"Rare","ilvl":68,"identified":true,"properties":[{"name":"閃避值","values":[["90",0]],"displayMode":0,"type":17},{"name":"能量護盾","values":[["19",0]],"displayMode":0,"type":18}],"requirements":[{"name":"等級","values":[["50",0]],"displayMode":0,"type":62},{"name":"敏捷","values":[["39",0]],"displayMode":1,"type":64},{"name":"智慧","values":[["39",0]],"displayMode":1,"type":65}],"explicitMods":["+24 智慧","攻擊附加 5 至 10 物理傷害","+86 最大生命","+36% 火焰抗性","+13% 閃電抗性"],"craftedMods":["25% 物理傷害轉換為閃電傷害"],"frameType":2,"frameTypeId":"Rare","x":10,"y":5,"inventoryId":"Stash13","socketedItems":[]},{"verified":false,"w":1,"h":1,"icon":"https://webtw.poecdn.com/gen/image/WzI1LDE0LHsiZiI6IjJESXRlbXMvUmluZ3MvRGlhbW9uZFJpbmciLCJ3IjoxLCJoIjoxLCJzY2FsZSI6MX1d/d07e3dfbb6/DiamondRing.png","league":"標準模式","id":"e67f0e4c6097295ba3856d41814f22fa5b57958d2014f8d5161a15cf8a97b56d","name":"亂世 指套","typeLine":"寶鑽戒指","baseType":"寶鑽戒指","rarity":"Rare","ilvl":72,"identified":true,"requirements":[{"name":"等級","values":[["64",0]],"displayMode":0,"type":62}],"implicitMods":["增加 24% 全域暴擊率"],"explicitMods":["+27 最大生命","+37 最大魔力","+16% 全部元素抗性","+44% 火焰抗性","+20% 冰冷抗性"],"craftedMods":["非引導施放技能 -8 總魔力消耗"],"frameType":2,"frameTypeId":"Rare","x":8,"y":7,"inventoryId":"Stash13"},{"verified":false,"w":2,"h":1,"icon":"https://webtw.poecdn.com/gen/image/WzI1LDE0LHsiZiI6IjJESXRlbXMvQmVsdHMvQmVsdDMiLCJ3IjoyLCJoIjoxLCJzY2FsZSI6MX1d/93af17affd/Belt3.png","league":"標準模式","id":"c5591bf1c9972c421da539eba665f4db84896aa1d58e1603f2f6037fc2ad5da6","name":"獸語 護帶","typeLine":"皮革腰帶","baseType":"皮革腰帶","rarity":"Rare","ilvl":70,"identified":true,"requirements":[{"name":"等級","values":[["51",0]],"displayMode":0,"type":62}],"implicitMods":["+36 最大生命"],"explicitMods":["+315 點護甲","+97 最大生命","+32% 火焰抗性","+26% 閃電抗性","增加 25% 暈眩恢復和格擋恢復"],"frameType":2,"frameTypeId":"Rare","x":4,"y":0,"inventoryId":"Stash13"},{"verified":false,"w":1,"h":1,"icon":"https://webtw.poecdn.com/gen/image/WzI1LDE0LHsiZiI6IjJESXRlbXMvSmV3ZWxzL2Jhc2ljZGV4IiwidyI6MSwiaCI6MSwic2NhbGUiOjF9XQ/9ed22a2b94/basicdex.png","league":"標準模式","id":"4a1dd744e5413749d468897ae260f54fa58d76b4ca231489600ab4d8c8c809ea","name":"暮色 裂毀者","typeLine":"翠綠珠寶","baseType":"翠綠珠寶","rarity":"Rare","ilvl":82,"identified":true,"explicitMods":["增加 6% 全域命中值","增加 8% 全域暴擊率","+13% 近戰暴擊加成","增加 6% 最大生命"],"descrText":"放置到一個天賦樹的珠寶插槽中以產生效果。右鍵點擊以移出插槽。","frameType":2,"frameTypeId":"Rare","x":8,"y":8,"inventoryId":"Stash13"},{"verified":false,"w":1,"h":3,"icon":"https://webtw.poecdn.com/gen/image/WzI1LDE0LHsiZiI6IjJESXRlbXMvV2VhcG9ucy9PbmVIYW5kV2VhcG9ucy9EYWdnZXJzL0RhZ2dlcjciLCJ3IjoxLCJoIjozLCJzY2FsZSI6MX1d/61e8f27cc5/Dagger7.png","league":"標準模式","id":"5d0f4e82248b899e7149c5295586533d2ff126ce3f7f62763d00a4fccf8742c0","sockets":[{"group":0,"attr":"D","sColour":"G"},{"group":0,"attr":"D","sColour":"G"},{"group":0,"attr":"I","sColour":"B"}],"name":"勝利 鋒刃","typeLine":"帝國雙刃匕","baseType":"帝國雙刃匕","rarity":"Rare","ilvl":74,"identified":true,"properties":[{"name":"符紋匕首","values":[],"displayMode":0},{"name":"物理傷害","values":[["18-73",0]],"displayMode":0,"type":9},{"name":"暴擊率","values":[["8.50%",0]],"displayMode":0,"type":12},{"name":"每秒攻擊次數","values":[["1.50",0]],"displayMode":0,"type":13},{"name":"武器距離: {0} 米","values":[["1",0]],"displayMode":3,"type":14}],"requirements":[{"name":"等級","values":[["66",0]],"displayMode":0,"type":62},{"name":"敏捷","values":[["95",0]],"displayMode":1,"type":64},{"name":"智慧","values":[["131",0]],"displayMode":1,"type":65}],"implicitMods":["增加 30% 全域暴擊率"],"explicitMods":["增加 36% 法術傷害","法術附加 3 至 126 閃電傷害","增加 20% 法術暴擊率","+38% 全域暴擊加成","全部閃電法術技能寶石等級 +1","+38% 冰冷抗性"],"frameType":2,"frameTypeId":"Rare","x":8,"y":9,"inventoryId":"Stash13","socketedItems":[]},{"verified":false,"w":2,"h":3,"icon":"https://webtw.poecdn.com/gen/image/WzI1LDE0LHsiZiI6IjJESXRlbXMvQXJtb3Vycy9Cb2R5QXJtb3Vycy9Cb2R5RGV4SW50NEMiLCJ3IjoyLCJoIjozLCJzY2FsZSI6MSwic2VhcmluZyI6dHJ1ZSwidGFuZ2xlZCI6dHJ1ZX1d/aa9c69066e/BodyDexInt4C.png","league":"標準模式","id":"86d71911bf0face257e738e3c797e691c060233e7b489a1e2f48d038d009276f","searing":true,"tangled":true,"sockets":[{"group":0,"attr":"S","sColour":"R"},{"group":0,"attr":"I","sColour":"B"},{"group":0,"attr":"D","sColour":"G"},{"group":0,"attr":"I","sColour":"B"},{"group":0,"attr":"I","sColour":"B"},{"group":0,"attr":"D","sColour":"G"}],"name":"鷹翼 護障","typeLine":"亡者護甲","baseType":"亡者護甲","rarity":"Rare","ilvl":85,"identified":true,"properties":[{"name":"品質","values":[["+20%",1]],"displayMode":0,"type":6},{"name":"閃避值","values":[["2352",1]],"displayMode":0,"type":17},{"name":"能量護盾","values":[["571",1]],"displayMode":0,"type":18}],"requirements":[{"name":"等級","values":[["84",0]],"displayMode":0,"type":62},{"name":"敏捷","values":[["173",0]],"displayMode":1,"type":64},{"name":"智慧","values":[["173",0]],"displayMode":1,"type":65}],"implicitMods":["增加 9% 最大能量護盾","增加 15% 閃電傷害"],"explicitMods":["+33 智慧","+152 點閃避值","增加 100% 閃避與能量護盾","+72 最大能量護盾","+29 最大生命"],"frameType":2,"frameTypeId":"Rare","x":4,"y":5,"inventoryId":"Stash13","socketedItems":[]},{"verified":false,"w":1,"h":1,"icon":"https://webtw.poecdn.com/gen/image/WzI1LDE0LHsiZiI6IjJESXRlbXMvUmluZ3MvSGVpc3RSaW5nMURhcmsiLCJ3IjoxLCJoIjoxLCJzY2FsZSI6MX1d/50914baa93/HeistRing1Dark.png","league":"標準模式","id":"b65d7fc3700a4e7febe7edf57eaf220396d7c3500e8a8f3faef5363dffc97eae","name":"劇痛 閃耀之指","typeLine":"螺旋戒指","baseType":"螺旋戒指","rarity":"Rare","ilvl":82,"identified":true,"split":true,"requirements":[{"name":"等級","values":[["65",0]],"displayMode":0,"type":62}],"implicitMods":["允許前綴 -2","允許後綴 +1","固定詞綴不能被改變","增加 50% 後綴大小"],"explicitMods":["+76 力量","+81 敏捷","+13 智慧","攻擊附加 1 至 15 閃電傷害"],"craftedMods":["+34% 火焰抗性"],"frameType":2,"frameTypeId":"Rare","x":10,"y":0,"inventoryId":"Stash13"},{"verified":false,"w":1,"h":1,"icon":"https://webtw.poecdn.com/gen/image/WzI1LDE0LHsiZiI6IjJESXRlbXMvUmluZ3MvVG9wYXpTYXBwaGlyZSIsInciOjEsImgiOjEsInNjYWxlIjoxfV0/0c211c12b4/TopazSapphire.png","league":"標準模式","id":"aa324eb7c0dc4997d764d382253360836053943271d1a63f387f01d6aad5267e","name":"惡行 之眼","typeLine":"雙玉戒指","baseType":"雙玉戒指","rarity":"Rare","ilvl":80,"identified":true,"requirements":[{"name":"等級","values":[["48",0]],"displayMode":0,"type":62}],"implicitMods":["+12% 冰冷與閃電抗性"],"explicitMods":["+69 最大生命","+41% 冰冷抗性","+25% 混沌抗性"],"craftedMods":["+9% 火焰和混沌抗性"],"frameType":2,"frameTypeId":"Rare","x":9,"y":7,"inventoryId":"Stash13"},{"verified":false,"w":1,"h":1,"icon":"https://webtw.poecdn.com/gen/image/WzI1LDE0LHsiZiI6IjJESXRlbXMvUmluZ3MvUmluZzIiLCJ3IjoxLCJoIjoxLCJzY2FsZSI6MX1d/6e12710920/Ring2.png","league":"標準模式","id":"ca79836a1adea887dd7a3e0b7aaa5cc60045dd72edb0e7a1b975ce24a2161051","influences":{"hunter":true},"name":"邪風 彎環","typeLine":"珊瑚戒指","baseType":"珊瑚戒指","rarity":"Rare","ilvl":83,"identified":true,"requirements":[{"name":"等級","values":[["64",0]],"displayMode":0,"type":62}],"implicitMods":["+26 最大生命"],"explicitMods":["+13 智慧","攻擊附加 5 至 12 火焰傷害","+16% 全部元素抗性","增加 9% 中毒持續時間","增加 22% 中毒傷害"],"craftedMods":["+44 最大生命"],"frameType":2,"frameTypeId":"Rare","x":5,"y":11,"inventoryId":"Stash13"},{"verified":false,"w":2,"h":4,"icon":"https://webtw.poecdn.com/gen/image/WzI1LDE0LHsiZiI6IjJESXRlbXMvV2VhcG9ucy9Ud29IYW5kV2VhcG9ucy9Cb3dzL0JvdzciLCJ3IjoyLCJoIjo0LCJzY2FsZSI6MX1d/1e6a3da9aa/Bow7.png","league":"標準模式","id":"92b3553cfc3d7346ae38933f3597375ba280bc0f0369836b5bb3b90fd3051b00","sockets":[{"group":0,"attr":"D","sColour":"G"},{"group":0,"attr":"I","sColour":"B"},{"group":0,"attr":"D","sColour":"G"},{"group":0,"attr":"S","sColour":"R"},{"group":0,"attr":"D","sColour":"G"},{"group":0,"attr":"D","sColour":"G"}],"name":"遺忘 破城弩","typeLine":"帝國之弓","baseType":"帝國之弓","rarity":"Rare","ilvl":100,"identified":true,"properties":[{"name":"弓","values":[],"displayMode":0},{"name":"物理傷害","values":[["29-117",0]],"displayMode":0,"type":9},{"name":"元素傷害","values":[["40-70",4]],"displayMode":0,"type":10},{"name":"暴擊率","values":[["6.25%",1]],"displayMode":0,"type":12},{"name":"每秒攻擊次數","values":[["1.45",0]],"displayMode":0,"type":13}],"requirements":[{"name":"等級","values":[["66",0]],"displayMode":0,"type":62},{"name":"敏捷","values":[["212",0]],"displayMode":1,"type":64}],"implicitMods":["攻擊技能增加 22% 元素傷害"],"explicitMods":["附加 40 至 70 火焰傷害","+6% 火焰抗性","增加 86% 元素傷害","傷害穿透 14% 火焰抗性"],"craftedMods":["增加 25% 暴擊率"],"frameType":2,"frameTypeId":"Rare","x":2,"y":0,"inventoryId":"Stash13","socketedItems":[]},{"verified":false,"w":1,"h":1,"icon":"https://webtw.poecdn.com/gen/image/WzI1LDE0LHsiZiI6IjJESXRlbXMvQW11bGV0cy9BZ2F0ZUFtdWxldCIsInciOjEsImgiOjEsInNjYWxlIjoxfV0/710a5a8ec4/AgateAmulet.png","league":"標準模式","id":"27b77a1631333b6aa51901cef6453771d28397dd6e4f5c6599d48b58442086e2","name":"苦痛 聖符","typeLine":"瑪瑙護身符","baseType":"瑪瑙護身符","rarity":"Rare","ilvl":85,"identified":true,"requirements":[{"name":"等級","values":[["61",0]],"displayMode":0,"type":62}],"implicitMods":["+24 力量和智慧"],"explicitMods":["+13 智慧","增加 22% 護甲","+41 最大能量護盾","+32% 冰冷抗性","+22% 閃電抗性"],"craftedMods":["增加 19% 最大能量護盾"],"frameType":2,"frameTypeId":"Rare","x":1,"y":6,"inventoryId":"Stash13"},{"verified":false,"w":1,"h":1,"icon":"https://webtw.poecdn.com/gen/image/WzI1LDE0LHsiZiI6IjJESXRlbXMvUmluZ3MvUmluZzciLCJ3IjoxLCJoIjoxLCJzY2FsZSI6MX1d/0e04df86a3/Ring7.png","league":"標準模式","id":"a9b95fa6b8f172945da2636a0e854b809f459cc8d8bfb4853e27e4fb7f667899","name":"暮色 魂掌","typeLine":"紅玉戒指","baseType":"紅玉戒指","rarity":"Rare","ilvl":77,"identified":true,"requirements":[{"name":"等級","values":[["54",0]],"displayMode":0,"type":62}],"implicitMods":["+25% 火焰抗性"],"explicitMods":["攻擊附加 1 至 2 物理傷害","增加 11% 物品稀有度","+35% 火焰抗性","+38% 冰冷抗性"],"craftedMods":["+50 最大生命"],"frameType":2,"frameTypeId":"Rare","x":0,"y":8,"inventoryId":"Stash13"},{"verified":false,"w":2,"h":3,"icon":"https://webtw.poecdn.com/gen/image/WzI1LDE0LHsiZiI6IjJESXRlbXMvQXJtb3Vycy9Cb2R5QXJtb3Vycy9Cb2R5U3RyRGV4MkMiLCJ3IjoyLCJoIjozLCJzY2FsZSI6MX1d/60a6d7b58c/BodyStrDex2C.png","league":"標準模式","id":"cefbc767745f4cada1b4a15a2bea982311bca17786ed57c26b8da73a2d31c4a4","sockets":[{"group":0,"attr":"I","sColour":"B"},{"group":0,"attr":"I","sColour":"B"},{"group":0,"attr":"I","sColour":"B"},{"group":0,"attr":"D","sColour":"G"},{"group":0,"attr":"I","sColour":"B"},{"group":0,"attr":"S","sColour":"R"}],"name":"漩渦 覆身","typeLine":"指揮者鎖甲","baseType":"指揮者鎖甲","rarity":"Rare","ilvl":65,"identified":true,"properties":[{"name":"護甲","values":[["297",1]],"displayMode":0,"type":16},{"name":"閃避值","values":[["296",1]],"displayMode":0,"type":17}],"requirements":[{"name":"等級","values":[["64",0]],"displayMode":0,"type":62},{"name":"力量","values":[["73",0]],"displayMode":1,"type":63},{"name":"敏捷","values":[["73",0]],"displayMode":1,"type":64}],"explicitMods":["+9 點護甲","+8 點閃避值","+117 最大生命","+37% 火焰抗性","反射 9 物理傷害給近戰攻擊者"],"frameType":2,"frameTypeId":"Rare","x":0,"y":0,"inventoryId":"Stash13","socketedItems":[]},{"verified":false,"w":2,"h":3,"icon":"https://webtw.poecdn.com/gen/image/WzI1LDE0LHsiZiI6IjJESXRlbXMvQXJtb3Vycy9Cb2R5QXJtb3Vycy9Cb2R5U3RyM0MiLCJ3IjoyLCJoIjozLCJzY2FsZSI6MX1d/09903268a5/BodyStr3C.png","league":"標準模式","id":"ca1b6ae61b0440bfad5a6ca7e7bd889c51043de1d025aeb8aa9ea3d4c60ba690","sockets":[{"group":0,"attr":"S","sColour":"R"},{"group":0,"attr":"S","sColour":"R"},{"group":0,"attr":"I","sColour":"B"},{"group":0,"attr":"G","sColour":"W"},{"group":0,"attr":"S","sColour":"R"},{"group":0,"attr":"G","sColour":"W"}],"name":"劇痛 堅殼","typeLine":"莊嚴之鎧","baseType":"莊嚴之鎧","rarity":"Rare","ilvl":68,"identified":true,"properties":[{"name":"品質","values":[["+20%",1]],"displayMode":0,"type":6},{"name":"護甲","values":[["821",1]],"displayMode":0,"type":16}],"requirements":[{"name":"等級","values":[["53",0]],"displayMode":0,"type":62},{"name":"力量","values":[["145",0]],"displayMode":1,"type":63}],"explicitMods":["+34 力量","+60 點護甲","增加 16% 護甲","+110 最大生命","2% 額外物理傷害減免"],"frameType":2,"frameTypeId":"Rare","x":10,"y":9,"inventoryId":"Stash13","socketedItems":[]},{"verified":false,"w":1,"h":1,"icon":"https://webtw.poecdn.com/gen/image/WzI1LDE0LHsiZiI6IjJESXRlbXMvUmluZ3MvQnJlYWNoUmluZyIsInciOjEsImgiOjEsInNjYWxlIjoxfV0/c21b912df7/BreachRing.png","league":"標準模式","id":"e2dc7c27886db68b1339342f6b94e1679725db50b84ccd2e6fbfb0e29ff15465","name":"不祥 螺旋","typeLine":"裂痕戒指","baseType":"裂痕戒指","rarity":"Rare","ilvl":79,"identified":true,"corrupted":true,"requirements":[{"name":"等級","values":[["57",0]],"displayMode":0,"type":62}],"implicitMods":["裂痕中此道具屬性有雙倍效果"],"explicitMods":["+27 敏捷","攻擊附加 2 至 43 閃電傷害","+78 最大生命","+44% 火焰抗性","+28% 閃電抗性"],"frameType":2,"frameTypeId":"Rare","x":1,"y":8,"inventoryId":"Stash13"},{"verified":false,"w":1,"h":1,"icon":"https://webtw.poecdn.com/gen/image/WzI1LDE0LHsiZiI6IjJESXRlbXMvQW11bGV0cy9BbXVsZXQ1IiwidyI6MSwiaCI6MSwic2NhbGUiOjF9XQ/998c42287b/Amulet5.png","league":"標準模式","id":"66b4eeaccdd1e69808d16eaba03f501f23eb0e2bd699f4e6f1d6fd1d67acd150","name":"禍害 護心符","typeLine":"海玉護身符","baseType":"海玉護身符","rarity":"Rare","ilvl":83,"identified":true,"corrupted":true,"requirements":[{"name":"等級","values":[["64",0]],"displayMode":0,"type":62}],"implicitMods":["獲得等級 23 的火焰淨化技能","+1% 最大全部抗性"],"explicitMods":["攻擊附加 11 至 22 物理傷害","攻擊附加 11 至 21 火焰傷害","增加 15% 護甲","+14% 全部元素抗性","+19% 冰冷抗性"],"frameType":2,"frameTypeId":"Rare","x":0,"y":6,"inventoryId":"Stash13"},{"verified":false,"w":1,"h":3,"icon":"https://webtw.poecdn.com/gen/image/WzI1LDE0LHsiZiI6IjJESXRlbXMvV2VhcG9ucy9PbmVIYW5kV2VhcG9ucy9XYW5kcy9XYW5kMyIsInciOjEsImgiOjMsInNjYWxlIjoxfV0/6322bd53f5/Wand3.png","league":"標準模式","id":"4c3e374ec3058e153433dd1b4628762d44c02f2262e65666c6bc45ef7c9d7d39","sockets":[{"group":0,"attr":"I","sColour":"B"},{"group":0,"attr":"I","sColour":"B"},{"group":0,"attr":"I","sColour":"B"}],"name":"魔暴 靈曲","typeLine":"魔性法杖","baseType":"魔性法杖","rarity":"Rare","ilvl":80,"identified":true,"properties":[{"name":"法杖","values":[],"displayMode":0},{"name":"品質","values":[["+20%",1]],"displayMode":0,"type":6},{"name":"物理傷害","values":[["32-60",1]],"displayMode":0,"type":9},{"name":"元素傷害","values":[["74-134",4]],"displayMode":0,"type":10},{"name":"暴擊率","values":[["8.00%",0]],"displayMode":0,"type":12},{"name":"每秒攻擊次數","values":[["1.60",0]],"displayMode":0,"type":13}],"requirements":[{"name":"等級","values":[["60",0]],"displayMode":0,"type":62},{"name":"智慧","values":[["188",0]],"displayMode":1,"type":65}],"implicitMods":["增加 36% 法術傷害"],"explicitMods":["增加 29% 火焰傷害","附加 74 至 134 火焰傷害","法術附加 27 至 44 火焰傷害"],"craftedMods":["可以最多有 3 個工藝詞綴","使用技能時觸發插槽中的 1 個法術，有 8 秒冷卻時間\n以此方式觸發的法術有 150% 更多消耗","增加 41% 法術傷害","獲得等同 3% 非混沌傷害的額外混沌傷害"],"frameType":2,"frameTypeId":"Rare","x":9,"y":9,"inventoryId":"Stash13","socketedItems":[]},{"verified":false,"w":1,"h":1,"icon":"https://webtw.poecdn.com/gen/image/WzI1LDE0LHsiZiI6IjJESXRlbXMvQW11bGV0cy9UdXJxdW9pc2VBbXVsZXQiLCJ3IjoxLCJoIjoxLCJzY2FsZSI6MX1d/605b4da0e1/TurquoiseAmulet.png","league":"標準模式","id":"b1c220c8b711d893933b29aec0e02df1d31ab78e1e3fff1dccf664b4b2833879","name":"海怪 寶符","typeLine":"青玉護身符","baseType":"青玉護身符","rarity":"Rare","ilvl":83,"identified":true,"requirements":[{"name":"等級","values":[["57",0]],"displayMode":0,"type":62}],"implicitMods":["+23 敏捷和智慧"],"explicitMods":["+33 最大能量護盾","增加 20% 物品稀有度","+27% 火焰抗性","+42% 冰冷抗性"],"craftedMods":["+54 最大生命"],"frameType":2,"frameTypeId":"Rare","x":3,"y":9,"inventoryId":"Stash13"},{"verified":false,"w":2,"h":3,"icon":"https://webtw.poecdn.com/gen/image/WzI1LDE0LHsiZiI6IjJESXRlbXMvV2VhcG9ucy9Ud29IYW5kV2VhcG9ucy9Cb3dzL0JvdzIiLCJ3IjoyLCJoIjozLCJzY2FsZSI6MX1d/0fcc51afcd/Bow2.png","league":"標準模式","id":"032ca599d02d74a1abe530afcc7132df09dc2e0cfdef3d2f11ad1da707de2b1b","sockets":[{"group":0,"attr":"S","sColour":"R"},{"group":0,"attr":"S","sColour":"R"},{"group":0,"attr":"D","sColour":"G"},{"group":0,"attr":"D","sColour":"G"},{"group":0,"attr":"D","sColour":"G"},{"group":0,"attr":"D","sColour":"G"}],"name":"勁風 之雨","typeLine":"短弓","baseType":"短弓","rarity":"Rare","ilvl":50,"identified":true,"properties":[{"name":"弓","values":[],"displayMode":0},{"name":"品質","values":[["+20%",1]],"displayMode":0,"type":6},{"name":"物理傷害","values":[["7-19",1]],"displayMode":0,"type":9},{"name":"暴擊率","values":[["5.00%",0]],"displayMode":0,"type":12},{"name":"每秒攻擊次數","values":[["1.69",1]],"displayMode":0,"type":13}],"requirements":[{"name":"等級","values":[["64",0]],"displayMode":0,"type":62},{"name":"敏捷","values":[["26",0]],"displayMode":1,"type":64}],"explicitMods":["此物品插槽中寶石等級 +1","此物品插槽中弓寶石等級 +2","增加 13% 攻擊速度","每擊中一個敵人，獲得 5 生命"],"craftedMods":["+19% 火焰持續傷害加成"],"frameType":2,"frameTypeId":"Rare","x":6,"y":3,"inventoryId":"Stash13","socketedItems":[],"incubatedItem":{"name":"有價值通貨碎片或神諭之物","level":68,"progress":5532,"total":9929}},{"verified":false,"w":1,"h":1,"icon":"https://webtw.poecdn.com/gen/image/WzI1LDE0LHsiZiI6IjJESXRlbXMvQW11bGV0cy9BbXVsZXQ3IiwidyI6MSwiaCI6MSwic2NhbGUiOjEsImR1cGxpY2F0ZWQiOnRydWV9XQ/175dfff8b5/Amulet7.png","league":"標準模式","id":"43482e98e30115b7f44511bdb228a2c6dae2df0549a8eb333dcecfe61d437eb9","name":"毀滅 魔偶","typeLine":"黑曜護身符","baseType":"黑曜護身符","rarity":"Rare","ilvl":83,"identified":true,"duplicated":true,"requirements":[{"name":"等級","values":[["52",0]],"displayMode":0,"type":62}],"implicitMods":["+15 全能力"],"explicitMods":["+50 全能力","+72 智慧","對你的攻擊附加 20 至 30 火焰傷害","-50 最大能量護盾"],"frameType":2,"frameTypeId":"Rare","x":10,"y":3,"inventoryId":"Stash13"},{"verified":false,"w":1,"h":1,"icon":"https://webtw.poecdn.com/gen/image/WzI1LDE0LHsiZiI6IjJESXRlbXMvUmluZ3MvQWRhbWFudGluZVJpbmciLCJ3IjoxLCJoIjoxLCJzY2FsZSI6MX1d/04d7eaa12e/AdamantineRing.png","league":"標準模式","id":"ecb762c27b81173f899c435a307740d6be9a61db3c3cc0f1459900a64772714f","name":"精魂 指套","typeLine":"鋼鑄戒指","baseType":"鋼鑄戒指","rarity":"Rare","ilvl":82,"identified":true,"requirements":[{"name":"等級","values":[["80",0]],"displayMode":0,"type":62}],"implicitMods":["攻擊附加 4 至 11 物理傷害"],"explicitMods":["攻擊附加 4 至 9 物理傷害","增加 7% 攻擊速度","+16% 全部元素抗性","+9% 火焰抗性"],"craftedMods":["+48 最大生命"],"frameType":2,"frameTypeId":"Rare","x":2,"y":9,"inventoryId":"Stash13"},{"verified":false,"w":2,"h":2,"icon":"https://webtw.poecdn.com/gen/image/WzI1LDE0LHsiZiI6IjJESXRlbXMvQXJtb3Vycy9IZWxtZXRzL0JvbmVIZWxtIiwidyI6MiwiaCI6Miwic2NhbGUiOjF9XQ/81dc21096f/BoneHelm.png","league":"標準模式","id":"55096f891c3f9a0d4edc698e229b1fc7ca17b83c81188c2215020b872b809a6d","sockets":[{"group":0,"attr":"I","sColour":"B"},{"group":0,"attr":"I","sColour":"B"},{"group":0,"attr":"S","sColour":"R"},{"group":0,"attr":"I","sColour":"B"}],"name":"宿敵 皇家之冠","typeLine":"喚骨頭盔","baseType":"喚骨頭盔","rarity":"Rare","ilvl":85,"identified":true,"properties":[{"name":"護甲","values":[["197",0]],"displayMode":0,"type":16},{"name":"能量護盾","values":[["62",1]],"displayMode":0,"type":18}],"requirements":[{"name":"等級","values":[["73",0]],"displayMode":0,"type":62},{"name":"力量","values":[["76",0]],"displayMode":1,"type":63},{"name":"智慧","values":[["76",0]],"displayMode":1,"type":65}],"implicitMods":["增加 19% 召喚物所造成的傷害"],"explicitMods":["+22 最大能量護盾","+103 最大生命","+47% 火焰抗性","+44% 閃電抗性"],"frameType":2,"frameTypeId":"Rare","x":2,"y":4,"inventoryId":"Stash13","socketedItems":[]},{"verified":false,"w":2,"h":3,"icon":"https://webtw.poecdn.com/gen/image/WzI1LDE0LHsiZiI6IjJESXRlbXMvQXJtb3Vycy9Cb2R5QXJtb3Vycy9Cb2R5U3RyNEEiLCJ3IjoyLCJoIjozLCJzY2FsZSI6MX1d/7e1c29aacf/BodyStr4A.png","league":"標準模式","id":"293386a3e0760e3ff73fa03bebcad49153e96de349b1c574f4c7ed9b0207e8a4","sockets":[{"group":0,"attr":"I","sColour":"B"},{"group":0,"attr":"S","sColour":"R"},{"group":0,"attr":"D","sColour":"G"},{"group":0,"attr":"S","sColour":"R"}],"name":"邪風 隱袍","typeLine":"爭戰鱗甲","baseType":"爭戰鱗甲","rarity":"Rare","ilvl":83,"identified":true,"properties":[{"name":"品質","values":[["+20%",1]],"displayMode":0,"type":6},{"name":"護甲","values":[["513",1]],"displayMode":0,"type":16},{"name":"閃避值","values":[["513",1]],"displayMode":0,"type":17}],"requirements":[{"name":"等級","values":[["54",0]],"displayMode":0,"type":62},{"name":"力量","values":[["79",0]],"displayMode":1,"type":63},{"name":"敏捷","values":[["79",0]],"displayMode":1,"type":64}],"explicitMods":["+28 敏捷","增加 44% 護甲與閃避","+111 最大生命","增加 10% 最大生命","+22% 混沌抗性"],"craftedMods":["增加 7% 最大生命","增加 8% 最大魔力"],"frameType":2,"frameTypeId":"Rare","x":0,"y":9,"inventoryId":"Stash13","socketedItems":[]},{"verified":false,"w":2,"h":2,"icon":"https://webtw.poecdn.com/gen/image/WzI1LDE0LHsiZiI6IjJESXRlbXMvQXJtb3Vycy9HbG92ZXMvU3Bpa2VkR2xvdmVzIiwidyI6MiwiaCI6Miwic2NhbGUiOjF9XQ/d98a3475e1/SpikedGloves.png","league":"標準模式","id":"8dc82d0c2c186ea8e7bc808f88e5ad4c8c38dc60ffee87f0276cbf6b4be3d4bf","sockets":[{"group":0,"attr":"D","sColour":"G"},{"group":0,"attr":"I","sColour":"B"},{"group":0,"attr":"D","sColour":"G"},{"group":0,"attr":"S","sColour":"R"}],"name":"暴怒 護掌","typeLine":"釦釘手套","baseType":"釦釘手套","rarity":"Rare","ilvl":76,"identified":true,"properties":[{"name":"護甲","values":[["386",1]],"displayMode":0,"type":16}],"requirements":[{"name":"等級","values":[["70",0]],"displayMode":0,"type":62},{"name":"力量","values":[["95",0]],"displayMode":1,"type":63}],"implicitMods":["增加 17% 近戰傷害"],"explicitMods":["獲得等級 20 的傲貓祝福技能","+17 點護甲","+105 最大生命","+38% 火焰抗性","+20% 冰冷抗性"],"craftedMods":["增加 63% 護甲"],"frameType":2,"frameTypeId":"Rare","x":0,"y":4,"inventoryId":"Stash13","socketedItems":[]},{"verified":false,"w":2,"h":2,"icon":"https://webtw.poecdn.com/gen/image/WzI1LDE0LHsiZiI6IjJESXRlbXMvQXJtb3Vycy9Cb290cy9Cb290c1N0cjQiLCJ3IjoyLCJoIjoyLCJzY2FsZSI6MX1d/82bedfd1e0/BootsStr4.png","league":"標準模式","id":"9d852bc29d4b9daac172b02bc022fa2423c1463a4838b1aa5ba696b56a0b9ae1","sockets":[{"group":0,"attr":"S","sColour":"R"},{"group":0,"attr":"I","sColour":"B"},{"group":0,"attr":"S","sColour":"R"},{"group":0,"attr":"D","sColour":"G"}],"name":"遺忘 之途","typeLine":"巨人脛甲","baseType":"巨人脛甲","rarity":"Rare","ilvl":84,"identified":true,"properties":[{"name":"品質","values":[["+20%",1]],"displayMode":0,"type":6},{"name":"護甲","values":[["608",1]],"displayMode":0,"type":16}],"requirements":[{"name":"等級","values":[["68",0]],"displayMode":0,"type":62},{"name":"力量","values":[["120",0]],"displayMode":1,"type":63}],"explicitMods":["+55 力量","+122 點護甲","增加 31% 護甲","+46% 火焰抗性","+35% 混沌抗性","增加 30% 移動速度","增加 13% 暈眩恢復和格擋恢復"],"frameType":2,"frameTypeId":"Rare","x":6,"y":6,"inventoryId":"Stash13","socketedItems":[],"incubatedItem":{"name":"物品","level":68,"progress":6659,"total":9030}},{"verified":false,"w":2,"h":3,"icon":"https://webtw.poecdn.com/gen/image/WzI1LDE0LHsiZiI6IjJESXRlbXMvQXJtb3Vycy9Cb2R5QXJtb3Vycy9Cb2R5U3RyNEEiLCJ3IjoyLCJoIjozLCJzY2FsZSI6MX1d/7e1c29aacf/BodyStr4A.png","league":"標準模式","id":"86b3095c423690faca4cd3cc1fd75028c4d1dc224894ad0801005c4caeb694f5","sockets":[{"group":0,"attr":"S","sColour":"R"},{"group":0,"attr":"S","sColour":"R"},{"group":0,"attr":"S","sColour":"R"},{"group":0,"attr":"D","sColour":"G"},{"group":0,"attr":"D","sColour":"G"},{"group":1,"attr":"I","sColour":"B"}],"name":"災禍 韌衣","typeLine":"爭戰鱗甲","baseType":"爭戰鱗甲","rarity":"Rare","ilvl":82,"identified":true,"properties":[{"name":"護甲","values":[["413",1]],"displayMode":0,"type":16},{"name":"閃避值","values":[["575",1]],"displayMode":0,"type":17}],"requirements":[{"name":"等級","values":[["62",0]],"displayMode":0,"type":62},{"name":"力量","values":[["79",0]],"displayMode":1,"type":63},{"name":"敏捷","values":[["79",0]],"displayMode":1,"type":64}],"explicitMods":["+117 點閃避值","增加 39% 護甲與閃避","+117 最大生命","+34% 火焰抗性","+44% 冰冷抗性","+30% 閃電抗性","增加 17% 暈眩恢復和格擋恢復"],"frameType":2,"frameTypeId":"Rare","x":4,"y":2,"inventoryId":"Stash13","socketedItems":[]},{"verified":false,"w":2,"h":2,"icon":"https://webtw.poecdn.com/gen/image/WzI1LDE0LHsiZiI6IjJESXRlbXMvQXJtb3Vycy9TaGllbGRzL1NoaWVsZEludDYiLCJ3IjoyLCJoIjoyLCJzY2FsZSI6MX1d/404ef29c87/ShieldInt6.png","league":"標準模式","id":"dcc32965030604aec1c3487434f62b15d91ff50ffdb20dac86075eabbd6851ec","sockets":[{"group":0,"attr":"D","sColour":"G"},{"group":0,"attr":"I","sColour":"B"},{"group":0,"attr":"D","sColour":"G"}],"name":"苦痛 靈光","typeLine":"巨人魔盾","baseType":"巨人魔盾","rarity":"Rare","ilvl":84,"identified":true,"properties":[{"name":"格擋率","values":[["25%",0]],"displayMode":0,"type":15},{"name":"能量護盾","values":[["276",1]],"displayMode":0,"type":18}],"requirements":[{"name":"等級","values":[["68",0]],"displayMode":0,"type":62},{"name":"智慧","values":[["159",0]],"displayMode":1,"type":65}],"explicitMods":["+101 最大能量護盾","+20 最大魔力","+12% 全部元素抗性","+12% 閃電抗性"],"craftedMods":["增加 64% 能量護盾"],"frameType":2,"frameTypeId":"Rare","x":2,"y":10,"inventoryId":"Stash13","socketedItems":[]},{"verified":false,"w":2,"h":1,"icon":"https://webtw.poecdn.com/gen/image/WzI1LDE0LHsiZiI6IjJESXRlbXMvQmVsdHMvQmVsdDMiLCJ3IjoyLCJoIjoxLCJzY2FsZSI6MX1d/93af17affd/Belt3.png","league":"標準模式","id":"7583eb9b278123c8f6189d77eac566aeabbb846c2e509f91a6b31b85a54d7b38","name":"蛇牙 護帶","typeLine":"皮革腰帶","baseType":"皮革腰帶","rarity":"Rare","ilvl":62,"identified":true,"requirements":[{"name":"等級","values":[["43",0]],"displayMode":0,"type":62}],"implicitMods":["+25 最大生命"],"explicitMods":["+89 最大生命","+26% 火焰抗性","+31% 閃電抗性","增加 12% 藥劑生命恢復率","攻擊技能增加 17% 元素傷害"],"craftedMods":["+23% 冰冷抗性"],"frameType":2,"frameTypeId":"Rare","x":0,"y":7,"inventoryId":"Stash13"},{"verified":false,"w":2,"h":2,"icon":"https://webtw.poecdn.com/gen/image/WzI1LDE0LHsiZiI6IjJESXRlbXMvQXJtb3Vycy9TaGllbGRzL1NoaWVsZERleEludDIiLCJ3IjoyLCJoIjoyLCJzY2FsZSI6MX1d/db9355404e/ShieldDexInt2.png","league":"標準模式","id":"3e302541bda20384ca750f40a1023a5cb581dd836829b40709c7b37c55db3237","sockets":[{"group":0,"attr":"I","sColour":"B"},{"group":0,"attr":"I","sColour":"B"},{"group":0,"attr":"I","sColour":"B"}],"name":"亂世 真實之衛","typeLine":"榿木刺盾","baseType":"榿木刺盾","rarity":"Rare","ilvl":67,"identified":true,"properties":[{"name":"格擋率","values":[["24%",0]],"displayMode":0,"type":15},{"name":"閃避值","values":[["249",1]],"displayMode":0,"type":17},{"name":"能量護盾","values":[["51",1]],"displayMode":0,"type":18}],"requirements":[{"name":"等級","values":[["64",0]],"displayMode":0,"type":62},{"name":"敏捷","values":[["74",0]],"displayMode":1,"type":64},{"name":"智慧","values":[["74",0]],"displayMode":1,"type":65}],"implicitMods":["+2% 壓抑法術傷害率"],"explicitMods":["+79 最大生命","+3% 全部元素抗性","+34% 冰冷抗性","+32% 閃電抗性"],"craftedMods":["增加 19% 閃避與能量護盾","+14 最大生命"],"frameType":2,"frameTypeId":"Rare","x":8,"y":5,"inventoryId":"Stash13","socketedItems":[]},{"verified":false,"w":1,"h":1,"icon":"https://webtw.poecdn.com/gen/image/WzI1LDE0LHsiZiI6IjJESXRlbXMvQW11bGV0cy9BbXVsZXQzIiwidyI6MSwiaCI6MSwic2NhbGUiOjF9XQ/abb6811fa1/Amulet3.png","league":"標準模式","id":"d10787aa2cd303d11336a4b0c5681aca1d006f422b8d9dbf230abb263a03623e","name":"蒼空 花符","typeLine":"琥珀護身符","baseType":"琥珀護身符","rarity":"Rare","ilvl":76,"identified":true,"requirements":[{"name":"等級","values":[["40",0]],"displayMode":0,"type":62}],"implicitMods":["+25 力量"],"explicitMods":["+22% 全域暴擊加成","+113 最大生命","+22% 火焰抗性","+33% 冰冷抗性"],"frameType":2,"frameTypeId":"Rare","x":11,"y":0,"inventoryId":"Stash13"},{"verified":false,"w":2,"h":3,"icon":"https://webtw.poecdn.com/gen/image/WzI1LDE0LHsiZiI6IjJESXRlbXMvV2VhcG9ucy9PbmVIYW5kV2VhcG9ucy9TY2VwdGVycy9zY2VwdGVyOSIsInciOjIsImgiOjMsInNjYWxlIjoxfV0/151820601e/scepter9.png","league":"標準模式","id":"84cd2c08260783a2c0cb6aed8865c70d72d6173e8057eb7952379c004e5c5f2e","sockets":[{"group":0,"attr":"S","sColour":"R"},{"group":0,"attr":"D","sColour":"G"},{"group":0,"attr":"I","sColour":"B"}],"name":"海怪 之術","typeLine":"惡魔權杖","baseType":"惡魔權杖","rarity":"Rare","ilvl":78,"identified":true,"properties":[{"name":"權杖","values":[],"displayMode":0},{"name":"物理傷害","values":[["42-78",0]],"displayMode":0,"type":9},{"name":"暴擊率","values":[["7.00%",0]],"displayMode":0,"type":12},{"name":"每秒攻擊次數","values":[["1.30",0]],"displayMode":0,"type":13},{"name":"武器距離: {0} 米","values":[["1.1",0]],"displayMode":3,"type":14}],"requirements":[{"name":"等級","values":[["70",0]],"displayMode":0,"type":62},{"name":"力量","values":[["121",0]],"displayMode":1,"type":63},{"name":"智慧","values":[["113",0]],"displayMode":1,"type":65}],"implicitMods":["傷害穿透 6% 元素抗性"],"explicitMods":["增加 7% 法術傷害","增加 25% 冰冷傷害","增加 47% 閃電傷害","法術附加 17 至 27 火焰傷害","增加 45% 法術暴擊率","+18 最大魔力"],"craftedMods":["使用技能時觸發插槽中的 1 個法術，有 8 秒冷卻時間\n以此方式觸發的法術有 150% 更多消耗"],"frameType":2,"frameTypeId":"Rare","x":8,"y":0,"inventoryId":"Stash13","socketedItems":[]},{"verified":false,"w":2,"h":2,"icon":"https://webtw.poecdn.com/gen/image/WzI1LDE0LHsiZiI6IjJESXRlbXMvQXJtb3Vycy9Cb290cy9Cb290c1N0cjMiLCJ3IjoyLCJoIjoyLCJzY2FsZSI6MX1d/56efa25c50/BootsStr3.png","league":"標準模式","id":"dfed6fe310d76b139a7667c369567e53fd3af4171359a0887af38f179a04505e","sockets":[{"group":0,"attr":"S","sColour":"R"},{"group":1,"attr":"S","sColour":"R"},{"group":1,"attr":"S","sColour":"R"},{"group":1,"attr":"S","sColour":"R"}],"name":"腐屍 漫步","typeLine":"遠古脛甲","baseType":"遠古脛甲","rarity":"Rare","ilvl":71,"identified":true,"corrupted":true,"properties":[{"name":"護甲","values":[["166",0]],"displayMode":0,"type":16}],"requirements":[{"name":"等級","values":[["48",0]],"displayMode":0,"type":62},{"name":"力量","values":[["82",0]],"displayMode":1,"type":63}],"implicitMods":["+1 最大耐力球"],"explicitMods":["+31 最大生命","+40% 冰冷抗性","+13% 混沌抗性","增加 25% 移動速度"],"frameType":2,"frameTypeId":"Rare","x":2,"y":6,"inventoryId":"Stash13","socketedItems":[]},{"verified":false,"w":2,"h":1,"icon":"https://webtw.poecdn.com/gen/image/WzI1LDE0LHsiZiI6IjJESXRlbXMvQmVsdHMvQmVsdDYiLCJ3IjoyLCJoIjoxLCJzY2FsZSI6MSwic3ludGhlc2lzZWQiOnRydWV9XQ/0443c55839/Belt6.png","league":"標準模式","id":"c0023b24d29d1378d3286992df0f45f4c76d41b92bb5adf952db3b811420abb4","synthesised":true,"name":"蒼空 束靈","typeLine":"追憶之 扣釘腰帶","baseType":"扣釘腰帶","rarity":"Rare","ilvl":83,"identified":true,"requirements":[{"name":"等級","values":[["57",0]],"displayMode":0,"type":62}],"implicitMods":["攻擊技能增加 17% 元素傷害"],"explicitMods":["+48 最大生命","+45% 火焰抗性","+32% 閃電抗性","增加 24% 暈眩恢復和格擋恢復","增加 29% 藥劑魔力恢復率"],"frameType":2,"frameTypeId":"Rare","x":4,"y":1,"inventoryId":"Stash13"},{"verified":false,"w":1,"h":1,"icon":"https://webtw.poecdn.com/gen/image/WzI1LDE0LHsiZiI6IjJESXRlbXMvUmluZ3MvUmluZzciLCJ3IjoxLCJoIjoxLCJzY2FsZSI6MX1d/0e04df86a3/Ring7.png","league":"標準模式","id":"834dc3093c245489fbe8690349619fa89ab1c55060b994745f76542a343b8531","name":"漩渦 寶戒","typeLine":"紅玉戒指","baseType":"紅玉戒指","rarity":"Rare","ilvl":79,"identified":true,"requirements":[{"name":"等級","values":[["59",0]],"displayMode":0,"type":62}],"implicitMods":["+30% 火焰抗性"],"explicitMods":["+44 最大能量護盾","+40% 火焰抗性","+30% 冰冷抗性","+25% 閃電抗性"],"craftedMods":["+49 最大生命"],"frameType":2,"frameTypeId":"Rare","x":4,"y":11,"inventoryId":"Stash13"}]}